goggle0/__cli__.py
goggle0/__init__.py
goggle0/_version.py
goggle0/conf/about/__init__.yaml
goggle0/py.typed
goggle0-0.1.0.dist-info/LICENSE
goggle0-0.1.0.dist-info/METADATA
goggle0-0.1.0.dist-info/WHEEL
goggle0-0.1.0.dist-info/entry_points.txt
goggle0-0.1.0.dist-info/RECORD
