Metadata-Version: 2.1
Name: goggle0
Version: 0.1.0
Summary: goggle0 project
Home-page: https://siwon12.github.io/goggle0
License: MIT
Author: oh si won
Author-email: 202021022@chu.ac.kr
Requires-Python: >=3.8.1,<3.12
Classifier: License :: OSI Approved :: MIT License
Classifier: Programming Language :: Python :: 3
Classifier: Programming Language :: Python :: 3.9
Classifier: Programming Language :: Python :: 3.10
Classifier: Programming Language :: Python :: 3.11
Project-URL: Repository, https://github.com/siwon12/goggle0
